{
  "@context": "https://doi.org/10.5063/schema/codemeta-2.0",
  "@type": "SoftwareSourceCode",
  "name": "Syntavra",
  "version": "0.0.1",
  "developmentStatus": "pre-alpha",
  "description": "Pre-release local-first token and context optimization Agent Skill for AI coding tools, with exact recovery and receipt-based measurement.",
  "codeRepository": "https://github.com/Naveax/Syntavra",
  "programmingLanguage": "Python",
  "runtimePlatform": "Python 3.11+",
  "author": {
    "@type": "Person",
    "name": "Naveax"
  },
  "keywords": [
    "agent-skills",
    "ai-coding-tools",
    "cache-optimization",
    "codex",
    "context-optimization",
    "exact-recovery",
    "mcp",
    "persistent-memory",
    "pre-release",
    "repository-context",
    "reversible-compression",
    "schema-optimization",
    "signalbench",
    "token-attribution",
    "token-optimization",
    "tool-output-compaction"
  ]
}
